sqlar/__init__.py
sqlar/exceptions.py
sqlar/repository.py
sqlar-1.0.0.dist-info/LICENSE
sqlar-1.0.0.dist-info/METADATA
sqlar-1.0.0.dist-info/WHEEL
sqlar-1.0.0.dist-info/top_level.txt
sqlar-1.0.0.dist-info/RECORD
