Metadata-Version: 2.1
Name: sqlar
Version: 1.0.0
Summary: SQLAlchemy implementation for Python Persistance API (persipy)
Home-page: https://github.com/pristupa/sqlar
Author: Pavel V. Pristupa
Author-email: pristupa@gmail.com
License: UNKNOWN
Platform: UNKNOWN
Classifier: Programming Language :: Python :: 3
Classifier: License :: OSI Approved :: GNU General Public License v3 (GPLv3)
Classifier: Operating System :: OS Independent
Requires-Python: >=3.6
Requires-Dist: injector (==0.15.0)
Requires-Dist: persipy (==2.0.0)
Requires-Dist: sqlalchemy (==1.3.13)
